{"identity":{"bookId":"the_great_gatsby","title":"The Great Gatsby","author":"F. Scott Fitzgerald","publicationYear":1925,"language":"en"},"classification":{"genres":["classic","literary_fiction"],"readerLevel":{"lexile":1070,"label":"Upper Secondary / Adult"},"difficultyTier":"MEDIUM"},"structure":{"totalBites":100,"chapters":[{"chapterId":"ch1","title":"Chapter 1","biteRange":[1,12]},{"chapterId":"ch2","title":"Chapter 2","biteRange":[13,21]},{"chapterId":"ch3","title":"Chapter 3","biteRange":[22,33]},{"chapterId":"ch4","title":"Chapter 4","biteRange":[34,44]},{"chapterId":"ch5","title":"Chapter 5","biteRange":[45,53]},{"chapterId":"ch6","title":"Chapter 6","biteRange":[54,61]},{"chapterId":"ch7","title":"Chapter 7","biteRange":[62,79]},{"chapterId":"ch8","title":"Chapter 8","biteRange":[80,89]},{"chapterId":"ch9","title":"Chapter 9","biteRange":[90,100]}]},"learningFocus":{"primarySkills":["reading_comprehension","literary_analysis"],"secondarySkills":["inference","vocabulary_in_context"]},"social":{"topicTags":["american_dream","wealth","illusion"],"interestTags":["classics","1920s","tragedy"],"shareableAchievements":true},"badges":{"completionBadge":"badge_the_great_gatsby_complete","specialtyBadges":["badge_the_great_gatsby_symbolism_mastery"],"hiddenBadges":[{"id":"badge_the_great_gatsby_green_light","condition":"Complete all bites in Chapter 5 with >=90% accuracy"}]},"economics":{"price":{"currency":"USD","amount":0},"purchaseType":"included","includedInPlans":["standard","education"]},"assets":{"coverImage":"cover.png","badgeImages":["badge_complete.png","badge_specialty.png","badge_hidden.png"]},"analytics":{"estimatedReadTimeMinutes":243,"avgSessionMinutes":12,"engagementWeight":1.0},"version":"1.0.0","license":"public_domain"}